sila2comlib/__init__.py
sila2comlib/com/__init__.py
sila2comlib/com/serial_com.py
sila2comlib-0.2.0.dist-info/METADATA
sila2comlib-0.2.0.dist-info/WHEEL
sila2comlib-0.2.0.dist-info/top_level.txt
sila2comlib-0.2.0.dist-info/RECORD
